{
	"uuid":"64350b50-a810-4901-b86b-7a5106bdef2c",
	"title": "推荐频道-亚洲",

	"channels": [

		{
			"name":"nhk",
			"url": "http://nhkwtvglobal-i.akamaihd.net/hls/live/263941/nhkwtvglobal/index_1180.m3u8"
		},

		{
			"name": "Japan 24news",
			"url": "https://n24-cdn-live.ntv.co.jp/ch01/High.m3u8"
		},
		
		
		{
			"name": "韩国arirang",
			"url": "http://amdlive.ctnd.com.edgesuite.net/arirang_1ch/smil:arirang_1ch.smil/playlist.m3u8"
		},
		{
			"name": "韩国MBC",
			"url": "http://www.pickcom.co.kr:1935/sjp/live07/chunklist_w2107750490.m3u8"
		},
		{
			"name": "阿聯酋UAE SPORTS HD",
			"url": "http://dmiftvll.mangomolo.com/dubaisportshd/smil:dubaisportshd.smil/chunklist_b2000000.m3u8"
		}
		

	]

}
